{
  "round": 2,
  "research_question": "虚质生命的自主性边界：当系统开始建立内部模型，它在什么条件下从'被驱动'转变为'主动驱动'？",
  "generated_at": "2026-03-27T05:58:10.768846+00:00",
  "reviews": [
    {
      "source_change_id": "0",
      "source_dept": "science",
      "title": "Latent-WAM: Latent World Action Modeling for End-to-End Autonomous Driving",
      "url": "http://arxiv.org/abs/2603.24581v1",
      "categories": [
        "quant-ph",
        "physics.comp-ph"
      ],
      "abstract_preview": "[无abstract]",
      "scores": {
        "novelty": 3.0,
        "methodology": 5.0,
        "relevance": 7.0,
        "reliability": 5.0,
        "significance": 3.0,
        "overall": 4.5
      },
      "strengths": [
        "与自主性边界研究问题高度相关"
      ],
      "weaknesses": [
        "创新性存疑，需原文验证",
        "实际意义有限"
      ],
      "verdict": "major_revision",
      "notes": "基于标题+abstract关键词评分 | dept=science"
    },
    {
      "source_change_id": "1",
      "source_dept": "mind",
      "title": "Dynamical Systems in Cosmology: Reviewing An Alternative Approach",
      "url": "http://arxiv.org/abs/2603.24568v1",
      "categories": [
        "q-bio.OT"
      ],
      "abstract_preview": "[无abstract]",
      "scores": {
        "novelty": 3.0,
        "methodology": 3.0,
        "relevance": 3.0,
        "reliability": 3.0,
        "significance": 3.0,
        "overall": 2.7
      },
      "strengths": [],
      "weaknesses": [
        "创新性存疑，需原文验证",
        "方法论描述不足",
        "与研究问题关联较弱"
      ],
      "verdict": "reject",
      "notes": "基于标题+abstract关键词评分 | dept=mind"
    },
    {
      "source_change_id": "2",
      "source_dept": "mind",
      "title": "Coordinating Spot and Contract Supply in Freight Marketplaces",
      "url": "http://arxiv.org/abs/2603.24574v1",
      "categories": [
        "cs.CY",
        "cs.AI"
      ],
      "abstract_preview": "[无abstract]",
      "scores": {
        "novelty": 3.0,
        "methodology": 3.0,
        "relevance": 3.0,
        "reliability": 3.0,
        "significance": 3.0,
        "overall": 2.7
      },
      "strengths": [],
      "weaknesses": [
        "创新性存疑，需原文验证",
        "方法论描述不足",
        "与研究问题关联较弱"
      ],
      "verdict": "reject",
      "notes": "基于标题+abstract关键词评分 | dept=mind"
    },
    {
      "source_change_id": "3",
      "source_dept": "mind",
      "title": "Robust valley-polarized excitonic Mott states and doublons enabled by stacking-controlled moiré geometry",
      "url": "http://arxiv.org/abs/2603.24494v1",
      "categories": [
        "cs.CY",
        "cs.AI"
      ],
      "abstract_preview": "[无abstract]",
      "scores": {
        "novelty": 3.0,
        "methodology": 3.0,
        "relevance": 3.0,
        "reliability": 3.0,
        "significance": 3.0,
        "overall": 2.7
      },
      "strengths": [],
      "weaknesses": [
        "创新性存疑，需原文验证",
        "方法论描述不足",
        "与研究问题关联较弱"
      ],
      "verdict": "reject",
      "notes": "基于标题+abstract关键词评分 | dept=mind"
    },
    {
      "source_change_id": "4",
      "source_dept": "mind",
      "title": "A Modular Platooning and Vehicle Coordination Simulator for Research and Education",
      "url": "http://arxiv.org/abs/2603.24540v1",
      "categories": [
        "cs.CY",
        "cs.AI"
      ],
      "abstract_preview": "[无abstract]",
      "scores": {
        "novelty": 3.0,
        "methodology": 3.0,
        "relevance": 3.0,
        "reliability": 3.0,
        "significance": 3.0,
        "overall": 2.7
      },
      "strengths": [],
      "weaknesses": [
        "创新性存疑，需原文验证",
        "方法论描述不足",
        "与研究问题关联较弱"
      ],
      "verdict": "reject",
      "notes": "基于标题+abstract关键词评分 | dept=mind"
    },
    {
      "source_change_id": "5",
      "source_dept": "mind",
      "title": "Efficient photon-pair emission from a nanostructured resonator and its theoretical description",
      "url": "http://arxiv.org/abs/2603.24351v1",
      "categories": [
        "cs.CY",
        "cs.AI"
      ],
      "abstract_preview": "[无abstract]",
      "scores": {
        "novelty": 3.0,
        "methodology": 3.0,
        "relevance": 3.0,
        "reliability": 3.0,
        "significance": 3.0,
        "overall": 2.7
      },
      "strengths": [],
      "weaknesses": [
        "创新性存疑，需原文验证",
        "方法论描述不足",
        "与研究问题关联较弱"
      ],
      "verdict": "reject",
      "notes": "基于标题+abstract关键词评分 | dept=mind"
    },
    {
      "source_change_id": "6",
      "source_dept": "mind",
      "title": "DreamerAD: Efficient Reinforcement Learning via Latent World Model for Autonomous Driving",
      "url": "http://arxiv.org/abs/2603.24587v1",
      "categories": [
        "cs.CY",
        "cs.AI"
      ],
      "abstract_preview": "[无abstract]",
      "scores": {
        "novelty": 3.0,
        "methodology": 5.0,
        "relevance": 9.0,
        "reliability": 5.0,
        "significance": 3.0,
        "overall": 5.0
      },
      "strengths": [
        "与自主性边界研究问题高度相关"
      ],
      "weaknesses": [
        "创新性存疑，需原文验证",
        "实际意义有限"
      ],
      "verdict": "major_revision",
      "notes": "基于标题+abstract关键词评分 | dept=mind"
    },
    {
      "source_change_id": "7",
      "source_dept": "mind",
      "title": "Landau and fractionalized theories of periodically driven intertwined orders",
      "url": "http://arxiv.org/abs/2603.24592v1",
      "categories": [
        "cs.CY",
        "cs.AI"
      ],
      "abstract_preview": "[无abstract]",
      "scores": {
        "novelty": 3.0,
        "methodology": 3.0,
        "relevance": 3.0,
        "reliability": 3.0,
        "significance": 3.0,
        "overall": 2.7
      },
      "strengths": [],
      "weaknesses": [
        "创新性存疑，需原文验证",
        "方法论描述不足",
        "与研究问题关联较弱"
      ],
      "verdict": "reject",
      "notes": "基于标题+abstract关键词评分 | dept=mind"
    },
    {
      "source_change_id": "8",
      "source_dept": "mind",
      "title": "The role of spatial context and multitask learning in the detection of organic and conventional farming systems based on Sentinel-2 time series",
      "url": "http://arxiv.org/abs/2603.24552v1",
      "categories": [
        "cs.CY",
        "cs.AI"
      ],
      "abstract_preview": "[无abstract]",
      "scores": {
        "novelty": 3.0,
        "methodology": 3.0,
        "relevance": 5.0,
        "reliability": 3.0,
        "significance": 3.0,
        "overall": 3.2
      },
      "strengths": [],
      "weaknesses": [
        "创新性存疑，需原文验证",
        "方法论描述不足",
        "实际意义有限"
      ],
      "verdict": "reject",
      "notes": "基于标题+abstract关键词评分 | dept=mind"
    },
    {
      "source_change_id": "9",
      "source_dept": "mind",
      "title": "Landau and fractionalized theories of periodically driven intertwined orders",
      "url": "http://arxiv.org/abs/2603.24592v1",
      "categories": [
        "cs.CY",
        "cs.AI"
      ],
      "abstract_preview": "[无abstract]",
      "scores": {
        "novelty": 3.0,
        "methodology": 3.0,
        "relevance": 3.0,
        "reliability": 3.0,
        "significance": 3.0,
        "overall": 2.7
      },
      "strengths": [],
      "weaknesses": [
        "创新性存疑，需原文验证",
        "方法论描述不足",
        "与研究问题关联较弱"
      ],
      "verdict": "reject",
      "notes": "基于标题+abstract关键词评分 | dept=mind"
    },
    {
      "source_change_id": "10",
      "source_dept": "philosophy",
      "title": "Unlocking HST's Stellar Treasure Trove: Stellar Activity Minima for HAT-P-11 Offer Prime Windows for Transmission Spectroscopy",
      "url": "http://arxiv.org/abs/2603.24585v1",
      "categories": [
        "physics.hist-ph"
      ],
      "abstract_preview": "[无abstract]",
      "scores": {
        "novelty": 3.0,
        "methodology": 3.0,
        "relevance": 3.0,
        "reliability": 3.0,
        "significance": 3.0,
        "overall": 2.7
      },
      "strengths": [],
      "weaknesses": [
        "创新性存疑，需原文验证",
        "方法论描述不足",
        "与研究问题关联较弱"
      ],
      "verdict": "reject",
      "notes": "基于标题+abstract关键词评分 | dept=philosophy"
    },
    {
      "source_change_id": "11",
      "source_dept": "philosophy",
      "title": "Testing Dark Energy with Black Hole Ringdown",
      "url": "http://arxiv.org/abs/2603.23634v1",
      "categories": [
        "hep-th",
        "gr-qc"
      ],
      "abstract_preview": "[无abstract]",
      "scores": {
        "novelty": 3.0,
        "methodology": 3.0,
        "relevance": 3.0,
        "reliability": 3.0,
        "significance": 3.0,
        "overall": 2.7
      },
      "strengths": [],
      "weaknesses": [
        "创新性存疑，需原文验证",
        "方法论描述不足",
        "与研究问题关联较弱"
      ],
      "verdict": "reject",
      "notes": "基于标题+abstract关键词评分 | dept=philosophy"
    },
    {
      "source_change_id": "12",
      "source_dept": "philosophy",
      "title": "Cascading Failures and Critical Infrastructures in Future Renewable European Power Systems",
      "url": "http://arxiv.org/abs/2603.24529v1",
      "categories": [
        "hep-th",
        "gr-qc"
      ],
      "abstract_preview": "[无abstract]",
      "scores": {
        "novelty": 5.0,
        "methodology": 3.0,
        "relevance": 3.0,
        "reliability": 3.0,
        "significance": 3.0,
        "overall": 3.0
      },
      "strengths": [],
      "weaknesses": [
        "方法论描述不足",
        "与研究问题关联较弱",
        "实际意义有限"
      ],
      "verdict": "reject",
      "notes": "基于标题+abstract关键词评分 | dept=philosophy"
    },
    {
      "source_change_id": "13",
      "source_dept": "philosophy",
      "title": "Group Editing : Edit Multiple Images in One Go",
      "url": "http://arxiv.org/abs/2603.22883v2",
      "categories": [
        "physics.hist-ph"
      ],
      "abstract_preview": "[无abstract]",
      "scores": {
        "novelty": 3.0,
        "methodology": 3.0,
        "relevance": 3.0,
        "reliability": 3.0,
        "significance": 3.0,
        "overall": 2.7
      },
      "strengths": [],
      "weaknesses": [
        "创新性存疑，需原文验证",
        "方法论描述不足",
        "与研究问题关联较弱"
      ],
      "verdict": "reject",
      "notes": "基于标题+abstract关键词评分 | dept=philosophy"
    },
    {
      "source_change_id": "14",
      "source_dept": "philosophy",
      "title": "Chiral Epitaxy: Enantioselective Growth of Chiral Nanowires on Low-Symmetry Two-Dimensional Materials",
      "url": "http://arxiv.org/abs/2603.24565v1",
      "categories": [
        "physics.hist-ph"
      ],
      "abstract_preview": "[无abstract]",
      "scores": {
        "novelty": 3.0,
        "methodology": 3.0,
        "relevance": 3.0,
        "reliability": 3.0,
        "significance": 3.0,
        "overall": 2.7
      },
      "strengths": [],
      "weaknesses": [
        "创新性存疑，需原文验证",
        "方法论描述不足",
        "与研究问题关联较弱"
      ],
      "verdict": "reject",
      "notes": "基于标题+abstract关键词评分 | dept=philosophy"
    },
    {
      "source_change_id": "15",
      "source_dept": "philosophy",
      "title": "Polynomial Speedup in Diffusion Models with the Multilevel Euler-Maruyama Method",
      "url": "http://arxiv.org/abs/2603.24594v1",
      "categories": [
        "physics.hist-ph"
      ],
      "abstract_preview": "[无abstract]",
      "scores": {
        "novelty": 3.0,
        "methodology": 7.0,
        "relevance": 3.0,
        "reliability": 7.0,
        "significance": 3.0,
        "overall": 4.3
      },
      "strengths": [
        "研究设计有明确的实验或框架支撑"
      ],
      "weaknesses": [
        "创新性存疑，需原文验证",
        "与研究问题关联较弱",
        "实际意义有限"
      ],
      "verdict": "major_revision",
      "notes": "基于标题+abstract关键词评分 | dept=philosophy"
    },
    {
      "source_change_id": "16",
      "source_dept": "philosophy",
      "title": "Effective geometrostatics of spherical stars beyond general relativity",
      "url": "http://arxiv.org/abs/2603.24269v1",
      "categories": [
        "hep-th",
        "gr-qc"
      ],
      "abstract_preview": "[无abstract]",
      "scores": {
        "novelty": 3.0,
        "methodology": 3.0,
        "relevance": 3.0,
        "reliability": 3.0,
        "significance": 3.0,
        "overall": 2.7
      },
      "strengths": [],
      "weaknesses": [
        "创新性存疑，需原文验证",
        "方法论描述不足",
        "与研究问题关联较弱"
      ],
      "verdict": "reject",
      "notes": "基于标题+abstract关键词评分 | dept=philosophy"
    },
    {
      "source_change_id": "17",
      "source_dept": "philosophy",
      "title": "Effective geometrostatics of spherical stars beyond general relativity",
      "url": "http://arxiv.org/abs/2603.24269v1",
      "categories": [
        "hep-th",
        "gr-qc"
      ],
      "abstract_preview": "[无abstract]",
      "scores": {
        "novelty": 3.0,
        "methodology": 3.0,
        "relevance": 3.0,
        "reliability": 3.0,
        "significance": 3.0,
        "overall": 2.7
      },
      "strengths": [],
      "weaknesses": [
        "创新性存疑，需原文验证",
        "方法论描述不足",
        "与研究问题关联较弱"
      ],
      "verdict": "reject",
      "notes": "基于标题+abstract关键词评分 | dept=philosophy"
    },
    {
      "source_change_id": "18",
      "source_dept": "philosophy",
      "title": "Effective geometrostatics of spherical stars beyond general relativity",
      "url": "http://arxiv.org/abs/2603.24269v1",
      "categories": [
        "hep-th",
        "gr-qc"
      ],
      "abstract_preview": "[无abstract]",
      "scores": {
        "novelty": 3.0,
        "methodology": 3.0,
        "relevance": 3.0,
        "reliability": 3.0,
        "significance": 3.0,
        "overall": 2.7
      },
      "strengths": [],
      "weaknesses": [
        "创新性存疑，需原文验证",
        "方法论描述不足",
        "与研究问题关联较弱"
      ],
      "verdict": "reject",
      "notes": "基于标题+abstract关键词评分 | dept=philosophy"
    },
    {
      "source_change_id": "19",
      "source_dept": "philosophy",
      "title": "Ground-State Extraction of Heavy-Light Meson Semileptonic Decay Form Factors",
      "url": "http://arxiv.org/abs/2603.24491v1",
      "categories": [
        "hep-th",
        "gr-qc"
      ],
      "abstract_preview": "[无abstract]",
      "scores": {
        "novelty": 3.0,
        "methodology": 3.0,
        "relevance": 3.0,
        "reliability": 3.0,
        "significance": 3.0,
        "overall": 2.7
      },
      "strengths": [],
      "weaknesses": [
        "创新性存疑，需原文验证",
        "方法论描述不足",
        "与研究问题关联较弱"
      ],
      "verdict": "reject",
      "notes": "基于标题+abstract关键词评分 | dept=philosophy"
    },
    {
      "source_change_id": "20",
      "source_dept": "intelligence",
      "title": "YingMusic-Singer: Controllable Singing Voice Synthesis with Flexible Lyric Manipulation and Annotation-free Melody Guidance",
      "url": "http://arxiv.org/abs/2603.24589v1",
      "categories": [
        "cs.CL",
        "cs.AI"
      ],
      "abstract_preview": "[无abstract]",
      "scores": {
        "novelty": 3.0,
        "methodology": 3.0,
        "relevance": 3.0,
        "reliability": 3.0,
        "significance": 3.0,
        "overall": 2.7
      },
      "strengths": [],
      "weaknesses": [
        "创新性存疑，需原文验证",
        "方法论描述不足",
        "与研究问题关联较弱"
      ],
      "verdict": "reject",
      "notes": "基于标题+abstract关键词评分 | dept=intelligence"
    },
    {
      "source_change_id": "21",
      "source_dept": "engineering",
      "title": "Beam Test Characterization of Silicon Microstrip Detector Flight-Model Ladders for the AMS-02 Upgrade",
      "url": "http://arxiv.org/abs/2603.25085v1",
      "categories": [
        "cs.SE"
      ],
      "abstract_preview": "[无abstract]",
      "scores": {
        "novelty": 3.0,
        "methodology": 5.0,
        "relevance": 3.0,
        "reliability": 5.0,
        "significance": 3.0,
        "overall": 3.5
      },
      "strengths": [],
      "weaknesses": [
        "创新性存疑，需原文验证",
        "与研究问题关联较弱",
        "实际意义有限"
      ],
      "verdict": "major_revision",
      "notes": "基于标题+abstract关键词评分 | dept=engineering"
    },
    {
      "source_change_id": "22",
      "source_dept": "engineering",
      "title": "Vega: Learning to Drive with Natural Language Instructions",
      "url": "http://arxiv.org/abs/2603.25741v1",
      "categories": [
        "cs.OS"
      ],
      "abstract_preview": "[无abstract]",
      "scores": {
        "novelty": 3.0,
        "methodology": 3.0,
        "relevance": 5.0,
        "reliability": 3.0,
        "significance": 3.0,
        "overall": 3.2
      },
      "strengths": [],
      "weaknesses": [
        "创新性存疑，需原文验证",
        "方法论描述不足",
        "实际意义有限"
      ],
      "verdict": "reject",
      "notes": "基于标题+abstract关键词评分 | dept=engineering"
    },
    {
      "source_change_id": "23",
      "source_dept": "engineering",
      "title": "LACY: Simulating Expert Mentoring for Software Onboarding with Code Tours",
      "url": "http://arxiv.org/abs/2603.25391v1",
      "categories": [
        "cs.SE"
      ],
      "abstract_preview": "[无abstract]",
      "scores": {
        "novelty": 3.0,
        "methodology": 3.0,
        "relevance": 3.0,
        "reliability": 3.0,
        "significance": 3.0,
        "overall": 2.7
      },
      "strengths": [],
      "weaknesses": [
        "创新性存疑，需原文验证",
        "方法论描述不足",
        "与研究问题关联较弱"
      ],
      "verdict": "reject",
      "notes": "基于标题+abstract关键词评分 | dept=engineering"
    },
    {
      "source_change_id": "24",
      "source_dept": "engineering",
      "title": "SafeMath: Inference-time Safety improves Math Accuracy",
      "url": "http://arxiv.org/abs/2603.25201v1",
      "categories": [
        "cs.SE",
        "cs.LG"
      ],
      "abstract_preview": "[无abstract]",
      "scores": {
        "novelty": 5.0,
        "methodology": 3.0,
        "relevance": 3.0,
        "reliability": 3.0,
        "significance": 3.0,
        "overall": 3.0
      },
      "strengths": [],
      "weaknesses": [
        "方法论描述不足",
        "与研究问题关联较弱",
        "实际意义有限"
      ],
      "verdict": "reject",
      "notes": "基于标题+abstract关键词评分 | dept=engineering"
    },
    {
      "source_change_id": "25",
      "source_dept": "engineering",
      "title": "ShotStream: Streaming Multi-Shot Video Generation for Interactive Storytelling",
      "url": "http://arxiv.org/abs/2603.25746v1",
      "categories": [
        "cs.SE",
        "cs.LG"
      ],
      "abstract_preview": "[无abstract]",
      "scores": {
        "novelty": 3.0,
        "methodology": 3.0,
        "relevance": 3.0,
        "reliability": 3.0,
        "significance": 3.0,
        "overall": 2.7
      },
      "strengths": [],
      "weaknesses": [
        "创新性存疑，需原文验证",
        "方法论描述不足",
        "与研究问题关联较弱"
      ],
      "verdict": "reject",
      "notes": "基于标题+abstract关键词评分 | dept=engineering"
    },
    {
      "source_change_id": "26",
      "source_dept": "engineering",
      "title": "Robust continuous-variable multipartite entanglement in circular arrays of nonlinear waveguides",
      "url": "http://arxiv.org/abs/2603.25610v1",
      "categories": [
        "cs.SE",
        "cs.LG"
      ],
      "abstract_preview": "[无abstract]",
      "scores": {
        "novelty": 3.0,
        "methodology": 3.0,
        "relevance": 3.0,
        "reliability": 3.0,
        "significance": 3.0,
        "overall": 2.7
      },
      "strengths": [],
      "weaknesses": [
        "创新性存疑，需原文验证",
        "方法论描述不足",
        "与研究问题关联较弱"
      ],
      "verdict": "reject",
      "notes": "基于标题+abstract关键词评分 | dept=engineering"
    },
    {
      "source_change_id": "27",
      "source_dept": "engineering",
      "title": "On Bass numbers of graded components of local cohomology modules supported on $\\mathfrak{C}$-monomial ideals in mixed characteristic",
      "url": "http://arxiv.org/abs/2603.25604v1",
      "categories": [
        "cs.SE",
        "cs.OS"
      ],
      "abstract_preview": "[无abstract]",
      "scores": {
        "novelty": 3.0,
        "methodology": 3.0,
        "relevance": 3.0,
        "reliability": 3.0,
        "significance": 3.0,
        "overall": 2.7
      },
      "strengths": [],
      "weaknesses": [
        "创新性存疑，需原文验证",
        "方法论描述不足",
        "与研究问题关联较弱"
      ],
      "verdict": "reject",
      "notes": "基于标题+abstract关键词评分 | dept=engineering"
    },
    {
      "source_change_id": "28",
      "source_dept": "engineering",
      "title": "Less Gaussians, Texture More: 4K Feed-Forward Textured Splatting",
      "url": "http://arxiv.org/abs/2603.25745v1",
      "categories": [
        "cs.SE"
      ],
      "abstract_preview": "[无abstract]",
      "scores": {
        "novelty": 3.0,
        "methodology": 3.0,
        "relevance": 3.0,
        "reliability": 3.0,
        "significance": 3.0,
        "overall": 2.7
      },
      "strengths": [],
      "weaknesses": [
        "创新性存疑，需原文验证",
        "方法论描述不足",
        "与研究问题关联较弱"
      ],
      "verdict": "reject",
      "notes": "基于标题+abstract关键词评分 | dept=engineering"
    },
    {
      "source_change_id": "29",
      "source_dept": "engineering",
      "title": "ShotStream: Streaming Multi-Shot Video Generation for Interactive Storytelling",
      "url": "http://arxiv.org/abs/2603.25746v1",
      "categories": [
        "cs.SE"
      ],
      "abstract_preview": "[无abstract]",
      "scores": {
        "novelty": 3.0,
        "methodology": 3.0,
        "relevance": 3.0,
        "reliability": 3.0,
        "significance": 3.0,
        "overall": 2.7
      },
      "strengths": [],
      "weaknesses": [
        "创新性存疑，需原文验证",
        "方法论描述不足",
        "与研究问题关联较弱"
      ],
      "verdict": "reject",
      "notes": "基于标题+abstract关键词评分 | dept=engineering"
    },
    {
      "source_change_id": "30",
      "source_dept": "science",
      "title": "PSDesigner: Automated Graphic Design with a Human-Like Creative Workflow",
      "url": "http://arxiv.org/abs/2603.25738v1",
      "categories": [
        "physics.comp-ph"
      ],
      "abstract_preview": "[无abstract]",
      "scores": {
        "novelty": 3.0,
        "methodology": 3.0,
        "relevance": 3.0,
        "reliability": 3.0,
        "significance": 3.0,
        "overall": 2.7
      },
      "strengths": [],
      "weaknesses": [
        "创新性存疑，需原文验证",
        "方法论描述不足",
        "与研究问题关联较弱"
      ],
      "verdict": "reject",
      "notes": "基于标题+abstract关键词评分 | dept=science"
    },
    {
      "source_change_id": "31",
      "source_dept": "science",
      "title": "Nonlinear Information from DESI Luminous Red Galaxies: An Emulator-Based Analysis of Pre- and Post-Reconstruction Power Spectra",
      "url": "http://arxiv.org/abs/2603.25693v1",
      "categories": [
        "astro-ph.CO"
      ],
      "abstract_preview": "[无abstract]",
      "scores": {
        "novelty": 3.0,
        "methodology": 5.0,
        "relevance": 3.0,
        "reliability": 5.0,
        "significance": 3.0,
        "overall": 3.5
      },
      "strengths": [],
      "weaknesses": [
        "创新性存疑，需原文验证",
        "与研究问题关联较弱",
        "实际意义有限"
      ],
      "verdict": "major_revision",
      "notes": "基于标题+abstract关键词评分 | dept=science"
    },
    {
      "source_change_id": "32",
      "source_dept": "science",
      "title": "Critical curve of two-matrix models $ABBA$, $A\\{B,A\\}B$ and $ABAB$, Part I: Monte Carlo",
      "url": "http://arxiv.org/abs/2603.25715v1",
      "categories": [
        "astro-ph.CO"
      ],
      "abstract_preview": "[无abstract]",
      "scores": {
        "novelty": 3.0,
        "methodology": 5.0,
        "relevance": 3.0,
        "reliability": 5.0,
        "significance": 3.0,
        "overall": 3.5
      },
      "strengths": [],
      "weaknesses": [
        "创新性存疑，需原文验证",
        "与研究问题关联较弱",
        "实际意义有限"
      ],
      "verdict": "major_revision",
      "notes": "基于标题+abstract关键词评分 | dept=science"
    },
    {
      "source_change_id": "33",
      "source_dept": "science",
      "title": "Particle Physics and Gravitational Waves as complementary windows on the Universe",
      "url": "http://arxiv.org/abs/2603.25578v1",
      "categories": [
        "astro-ph.CO"
      ],
      "abstract_preview": "[无abstract]",
      "scores": {
        "novelty": 3.0,
        "methodology": 3.0,
        "relevance": 3.0,
        "reliability": 3.0,
        "significance": 3.0,
        "overall": 2.7
      },
      "strengths": [],
      "weaknesses": [
        "创新性存疑，需原文验证",
        "方法论描述不足",
        "与研究问题关联较弱"
      ],
      "verdict": "reject",
      "notes": "基于标题+abstract关键词评分 | dept=science"
    },
    {
      "source_change_id": "34",
      "source_dept": "science",
      "title": "Dynamics and stochastic resonance in a mathematical model of bistable phosphorylation and nuclear size control",
      "url": "http://arxiv.org/abs/2603.25518v1",
      "categories": [
        "astro-ph.CO"
      ],
      "abstract_preview": "[无abstract]",
      "scores": {
        "novelty": 3.0,
        "methodology": 5.0,
        "relevance": 3.0,
        "reliability": 5.0,
        "significance": 3.0,
        "overall": 3.5
      },
      "strengths": [],
      "weaknesses": [
        "创新性存疑，需原文验证",
        "与研究问题关联较弱",
        "实际意义有限"
      ],
      "verdict": "major_revision",
      "notes": "基于标题+abstract关键词评分 | dept=science"
    },
    {
      "source_change_id": "35",
      "source_dept": "mind",
      "title": "Concentration And Distribution of Container Flows In Mauritania's Maritime System (2019-2022)",
      "url": "http://arxiv.org/abs/2603.25678v1",
      "categories": [
        "cs.CY"
      ],
      "abstract_preview": "[无abstract]",
      "scores": {
        "novelty": 3.0,
        "methodology": 3.0,
        "relevance": 3.0,
        "reliability": 3.0,
        "significance": 3.0,
        "overall": 2.7
      },
      "strengths": [],
      "weaknesses": [
        "创新性存疑，需原文验证",
        "方法论描述不足",
        "与研究问题关联较弱"
      ],
      "verdict": "reject",
      "notes": "基于标题+abstract关键词评分 | dept=mind"
    },
    {
      "source_change_id": "36",
      "source_dept": "mind",
      "title": "Evaluating Language Models for Harmful Manipulation",
      "url": "http://arxiv.org/abs/2603.25326v1",
      "categories": [
        "cs.AI",
        "cs.CY"
      ],
      "abstract_preview": "[无abstract]",
      "scores": {
        "novelty": 3.0,
        "methodology": 5.0,
        "relevance": 3.0,
        "reliability": 5.0,
        "significance": 3.0,
        "overall": 3.5
      },
      "strengths": [],
      "weaknesses": [
        "创新性存疑，需原文验证",
        "与研究问题关联较弱",
        "实际意义有限"
      ],
      "verdict": "major_revision",
      "notes": "基于标题+abstract关键词评分 | dept=mind"
    },
    {
      "source_change_id": "37",
      "source_dept": "mind",
      "title": "Krylov-space anatomy and spread complexity of a disordered quantum spin chain",
      "url": "http://arxiv.org/abs/2603.25724v1",
      "categories": [
        "cs.AI",
        "cs.CY"
      ],
      "abstract_preview": "[无abstract]",
      "scores": {
        "novelty": 3.0,
        "methodology": 3.0,
        "relevance": 3.0,
        "reliability": 3.0,
        "significance": 3.0,
        "overall": 2.7
      },
      "strengths": [],
      "weaknesses": [
        "创新性存疑，需原文验证",
        "方法论描述不足",
        "与研究问题关联较弱"
      ],
      "verdict": "reject",
      "notes": "基于标题+abstract关键词评分 | dept=mind"
    },
    {
      "source_change_id": "38",
      "source_dept": "mind",
      "title": "Compiling molecular ultrastructure into neural dynamics",
      "url": "http://arxiv.org/abs/2603.25713v1",
      "categories": [
        "cs.AI",
        "cs.CY"
      ],
      "abstract_preview": "[无abstract]",
      "scores": {
        "novelty": 3.0,
        "methodology": 3.0,
        "relevance": 3.0,
        "reliability": 3.0,
        "significance": 3.0,
        "overall": 2.7
      },
      "strengths": [],
      "weaknesses": [
        "创新性存疑，需原文验证",
        "方法论描述不足",
        "与研究问题关联较弱"
      ],
      "verdict": "reject",
      "notes": "基于标题+abstract关键词评分 | dept=mind"
    },
    {
      "source_change_id": "39",
      "source_dept": "mind",
      "title": "Maximizing Qubit Throughput under Buffer Decoherence and Variability in Generation",
      "url": "http://arxiv.org/abs/2603.25482v1",
      "categories": [
        "cs.AI",
        "cs.CY"
      ],
      "abstract_preview": "[无abstract]",
      "scores": {
        "novelty": 3.0,
        "methodology": 3.0,
        "relevance": 3.0,
        "reliability": 3.0,
        "significance": 3.0,
        "overall": 2.7
      },
      "strengths": [],
      "weaknesses": [
        "创新性存疑，需原文验证",
        "方法论描述不足",
        "与研究问题关联较弱"
      ],
      "verdict": "reject",
      "notes": "基于标题+abstract关键词评分 | dept=mind"
    },
    {
      "source_change_id": "40",
      "source_dept": "mind",
      "title": "GridVAD: Open-Set Video Anomaly Detection via Spatial Reasoning over Stratified Frame Grids",
      "url": "http://arxiv.org/abs/2603.25467v1",
      "categories": [
        "cs.AI",
        "cs.CY"
      ],
      "abstract_preview": "[无abstract]",
      "scores": {
        "novelty": 3.0,
        "methodology": 3.0,
        "relevance": 3.0,
        "reliability": 3.0,
        "significance": 3.0,
        "overall": 2.7
      },
      "strengths": [],
      "weaknesses": [
        "创新性存疑，需原文验证",
        "方法论描述不足",
        "与研究问题关联较弱"
      ],
      "verdict": "reject",
      "notes": "基于标题+abstract关键词评分 | dept=mind"
    },
    {
      "source_change_id": "41",
      "source_dept": "mind",
      "title": "Evaluating Language Models for Harmful Manipulation",
      "url": "http://arxiv.org/abs/2603.25326v1",
      "categories": [
        "cs.AI",
        "cs.CY"
      ],
      "abstract_preview": "[无abstract]",
      "scores": {
        "novelty": 3.0,
        "methodology": 5.0,
        "relevance": 3.0,
        "reliability": 5.0,
        "significance": 3.0,
        "overall": 3.5
      },
      "strengths": [],
      "weaknesses": [
        "创新性存疑，需原文验证",
        "与研究问题关联较弱",
        "实际意义有限"
      ],
      "verdict": "major_revision",
      "notes": "基于标题+abstract关键词评分 | dept=mind"
    },
    {
      "source_change_id": "42",
      "source_dept": "mind",
      "title": "Voxtral TTS",
      "url": "http://arxiv.org/abs/2603.25551v1",
      "categories": [
        "cs.AI",
        "cs.CY"
      ],
      "abstract_preview": "[无abstract]",
      "scores": {
        "novelty": 3.0,
        "methodology": 3.0,
        "relevance": 3.0,
        "reliability": 3.0,
        "significance": 3.0,
        "overall": 2.7
      },
      "strengths": [],
      "weaknesses": [
        "创新性存疑，需原文验证",
        "方法论描述不足",
        "与研究问题关联较弱"
      ],
      "verdict": "reject",
      "notes": "基于标题+abstract关键词评分 | dept=mind"
    },
    {
      "source_change_id": "43",
      "source_dept": "philosophy",
      "title": "Parameterizing Dark Energy at the density level: A two-parameter alternative to CPL",
      "url": "http://arxiv.org/abs/2603.25735v1",
      "categories": [
        "physics.hist-ph"
      ],
      "abstract_preview": "[无abstract]",
      "scores": {
        "novelty": 3.0,
        "methodology": 3.0,
        "relevance": 3.0,
        "reliability": 3.0,
        "significance": 3.0,
        "overall": 2.7
      },
      "strengths": [],
      "weaknesses": [
        "创新性存疑，需原文验证",
        "方法论描述不足",
        "与研究问题关联较弱"
      ],
      "verdict": "reject",
      "notes": "基于标题+abstract关键词评分 | dept=philosophy"
    },
    {
      "source_change_id": "44",
      "source_dept": "science",
      "title": "ShotStream: Streaming Multi-Shot Video Generation for Interactive Storytelling",
      "url": "http://arxiv.org/abs/2603.25746v1",
      "categories": [
        "physics.comp-ph"
      ],
      "abstract_preview": "[无abstract]",
      "scores": {
        "novelty": 3.0,
        "methodology": 3.0,
        "relevance": 3.0,
        "reliability": 3.0,
        "significance": 3.0,
        "overall": 2.7
      },
      "strengths": [],
      "weaknesses": [
        "创新性存疑，需原文验证",
        "方法论描述不足",
        "与研究问题关联较弱"
      ],
      "verdict": "reject",
      "notes": "基于标题+abstract关键词评分 | dept=science"
    },
    {
      "source_change_id": "45",
      "source_dept": "science",
      "title": "Label-free Imaging of Single-Biomolecule Structure and Interaction by Stimulated Raman Photothermal Encoded Scattering",
      "url": "http://arxiv.org/abs/2603.25534v1",
      "categories": [
        "physics.comp-ph",
        "quant-ph"
      ],
      "abstract_preview": "[无abstract]",
      "scores": {
        "novelty": 3.0,
        "methodology": 3.0,
        "relevance": 3.0,
        "reliability": 3.0,
        "significance": 3.0,
        "overall": 2.7
      },
      "strengths": [],
      "weaknesses": [
        "创新性存疑，需原文验证",
        "方法论描述不足",
        "与研究问题关联较弱"
      ],
      "verdict": "reject",
      "notes": "基于标题+abstract关键词评分 | dept=science"
    },
    {
      "source_change_id": "46",
      "source_dept": "science",
      "title": "Uncertainty-Guided Label Rebalancing for CPS Safety Monitoring",
      "url": "http://arxiv.org/abs/2603.25670v1",
      "categories": [
        "physics.comp-ph",
        "quant-ph"
      ],
      "abstract_preview": "[无abstract]",
      "scores": {
        "novelty": 3.0,
        "methodology": 3.0,
        "relevance": 3.0,
        "reliability": 3.0,
        "significance": 3.0,
        "overall": 2.7
      },
      "strengths": [],
      "weaknesses": [
        "创新性存疑，需原文验证",
        "方法论描述不足",
        "与研究问题关联较弱"
      ],
      "verdict": "reject",
      "notes": "基于标题+abstract关键词评分 | dept=science"
    },
    {
      "source_change_id": "47",
      "source_dept": "science",
      "title": "Krylov-space anatomy and spread complexity of a disordered quantum spin chain",
      "url": "http://arxiv.org/abs/2603.25724v1",
      "categories": [
        "astro-ph.CO"
      ],
      "abstract_preview": "[无abstract]",
      "scores": {
        "novelty": 3.0,
        "methodology": 3.0,
        "relevance": 3.0,
        "reliability": 3.0,
        "significance": 3.0,
        "overall": 2.7
      },
      "strengths": [],
      "weaknesses": [
        "创新性存疑，需原文验证",
        "方法论描述不足",
        "与研究问题关联较弱"
      ],
      "verdict": "reject",
      "notes": "基于标题+abstract关键词评分 | dept=science"
    },
    {
      "source_change_id": "48",
      "source_dept": "science",
      "title": "ShotStream: Streaming Multi-Shot Video Generation for Interactive Storytelling",
      "url": "http://arxiv.org/abs/2603.25746v1",
      "categories": [
        "astro-ph.CO"
      ],
      "abstract_preview": "[无abstract]",
      "scores": {
        "novelty": 3.0,
        "methodology": 3.0,
        "relevance": 3.0,
        "reliability": 3.0,
        "significance": 3.0,
        "overall": 2.7
      },
      "strengths": [],
      "weaknesses": [
        "创新性存疑，需原文验证",
        "方法论描述不足",
        "与研究问题关联较弱"
      ],
      "verdict": "reject",
      "notes": "基于标题+abstract关键词评分 | dept=science"
    },
    {
      "source_change_id": "49",
      "source_dept": "intelligence",
      "title": "Evaluating Language Models for Harmful Manipulation",
      "url": "http://arxiv.org/abs/2603.25326v1",
      "categories": [
        "cs.AI",
        "cs.CY"
      ],
      "abstract_preview": "[无abstract]",
      "scores": {
        "novelty": 3.0,
        "methodology": 5.0,
        "relevance": 3.0,
        "reliability": 5.0,
        "significance": 3.0,
        "overall": 3.5
      },
      "strengths": [],
      "weaknesses": [
        "创新性存疑，需原文验证",
        "与研究问题关联较弱",
        "实际意义有限"
      ],
      "verdict": "major_revision",
      "notes": "基于标题+abstract关键词评分 | dept=intelligence"
    }
  ],
  "aggregated": {
    "total_reviewed": 50,
    "avg_overall": 2.96,
    "by_verdict": {
      "accept": 0,
      "minor_revision": 0,
      "major_revision": 10,
      "reject": 40
    },
    "top_papers": [
      "6",
      "0",
      "15",
      "21",
      "31"
    ]
  }
}